{
  "config": {
    "model_name": "meta-llama/Llama-3.2-1B",
    "dataset_path": "data/example_dataset.jsonl",
    "max_k": 1,
    "probe_type": "linear",
    "num_epochs": 1,
    "batch_size": 32,
    "learning_rate": 0.001
  },
  "metadata": {
    "model_name": "meta-llama/Llama-3.2-1B",
    "max_k": 1,
    "max_new_tokens": 20,
    "n_prompts": 10,
    "d_model": 2048,
    "vocab_size": 128256,
    "layers": [
      0,
      1,
      2,
      3,
      4,
      5,
      6,
      7,
      8,
      9,
      10,
      11,
      12,
      13,
      14,
      15
    ]
  },
  "results": {
    "layer0_k1": {
      "layer": 0,
      "k": 1,
      "train_accuracy": 0.14705882352941177,
      "train_loss": 11.690438747406006,
      "val_accuracy": 0.11188811188811189,
      "val_top5_accuracy": 0.3041958041958042,
      "val_loss": 11.572581079271105,
      "probe_path": "experiment_results/probes/k1/probe_layer_0_k1_linear.pt"
    },
    "layer1_k1": {
      "layer": 1,
      "k": 1,
      "train_accuracy": 0.11764705882352941,
      "train_loss": 11.790824699401856,
      "val_accuracy": 0.13636363636363635,
      "val_top5_accuracy": 0.2097902097902098,
      "val_loss": 11.41235786014133,
      "probe_path": "experiment_results/probes/k1/probe_layer_1_k1_linear.pt"
    },
    "layer2_k1": {
      "layer": 2,
      "k": 1,
      "train_accuracy": 0.08823529411764706,
      "train_loss": 11.734599494934082,
      "val_accuracy": 0.10839160839160839,
      "val_top5_accuracy": 0.2062937062937063,
      "val_loss": 11.429797490437826,
      "probe_path": "experiment_results/probes/k1/probe_layer_2_k1_linear.pt"
    },
    "layer3_k1": {
      "layer": 3,
      "k": 1,
      "train_accuracy": 0.07516339869281045,
      "train_loss": 11.658809089660645,
      "val_accuracy": 0.10839160839160839,
      "val_top5_accuracy": 0.2692307692307692,
      "val_loss": 11.212984614902073,
      "probe_path": "experiment_results/probes/k1/probe_layer_3_k1_linear.pt"
    },
    "layer4_k1": {
      "layer": 4,
      "k": 1,
      "train_accuracy": 0.0718954248366013,
      "train_loss": 11.67999906539917,
      "val_accuracy": 0.13636363636363635,
      "val_top5_accuracy": 0.2902097902097902,
      "val_loss": 11.122054100036621,
      "probe_path": "experiment_results/probes/k1/probe_layer_4_k1_linear.pt"
    },
    "layer5_k1": {
      "layer": 5,
      "k": 1,
      "train_accuracy": 0.0915032679738562,
      "train_loss": 11.599164485931396,
      "val_accuracy": 0.16083916083916083,
      "val_top5_accuracy": 0.34265734265734266,
      "val_loss": 11.043284946017796,
      "probe_path": "experiment_results/probes/k1/probe_layer_5_k1_linear.pt"
    },
    "layer6_k1": {
      "layer": 6,
      "k": 1,
      "train_accuracy": 0.07516339869281045,
      "train_loss": 11.65536117553711,
      "val_accuracy": 0.15734265734265734,
      "val_top5_accuracy": 0.3111888111888112,
      "val_loss": 11.140802383422852,
      "probe_path": "experiment_results/probes/k1/probe_layer_6_k1_linear.pt"
    },
    "layer7_k1": {
      "layer": 7,
      "k": 1,
      "train_accuracy": 0.09477124183006536,
      "train_loss": 11.640716171264648,
      "val_accuracy": 0.20279720279720279,
      "val_top5_accuracy": 0.35664335664335667,
      "val_loss": 11.04167037540012,
      "probe_path": "experiment_results/probes/k1/probe_layer_7_k1_linear.pt"
    },
    "layer8_k1": {
      "layer": 8,
      "k": 1,
      "train_accuracy": 0.05555555555555555,
      "train_loss": 11.619764518737792,
      "val_accuracy": 0.14685314685314685,
      "val_top5_accuracy": 0.25524475524475526,
      "val_loss": 11.028324127197266,
      "probe_path": "experiment_results/probes/k1/probe_layer_8_k1_linear.pt"
    },
    "layer9_k1": {
      "layer": 9,
      "k": 1,
      "train_accuracy": 0.10457516339869281,
      "train_loss": 11.640593719482421,
      "val_accuracy": 0.16433566433566432,
      "val_top5_accuracy": 0.32867132867132864,
      "val_loss": 11.049526850382486,
      "probe_path": "experiment_results/probes/k1/probe_layer_9_k1_linear.pt"
    },
    "layer10_k1": {
      "layer": 10,
      "k": 1,
      "train_accuracy": 0.10784313725490197,
      "train_loss": 11.53873233795166,
      "val_accuracy": 0.1993006993006993,
      "val_top5_accuracy": 0.3146853146853147,
      "val_loss": 10.759531762864855,
      "probe_path": "experiment_results/probes/k1/probe_layer_10_k1_linear.pt"
    },
    "layer11_k1": {
      "layer": 11,
      "k": 1,
      "train_accuracy": 0.11437908496732026,
      "train_loss": 11.522968101501466,
      "val_accuracy": 0.21328671328671328,
      "val_top5_accuracy": 0.3146853146853147,
      "val_loss": 10.784250365363228,
      "probe_path": "experiment_results/probes/k1/probe_layer_11_k1_linear.pt"
    },
    "layer12_k1": {
      "layer": 12,
      "k": 1,
      "train_accuracy": 0.11764705882352941,
      "train_loss": 11.337404727935791,
      "val_accuracy": 0.22727272727272727,
      "val_top5_accuracy": 0.3531468531468531,
      "val_loss": 10.379602220323351,
      "probe_path": "experiment_results/probes/k1/probe_layer_12_k1_linear.pt"
    },
    "layer13_k1": {
      "layer": 13,
      "k": 1,
      "train_accuracy": 0.1111111111111111,
      "train_loss": 11.20722541809082,
      "val_accuracy": 0.21328671328671328,
      "val_top5_accuracy": 0.3531468531468531,
      "val_loss": 10.273258845011393,
      "probe_path": "experiment_results/probes/k1/probe_layer_13_k1_linear.pt"
    },
    "layer14_k1": {
      "layer": 14,
      "k": 1,
      "train_accuracy": 0.08823529411764706,
      "train_loss": 10.835973072052003,
      "val_accuracy": 0.2062937062937063,
      "val_top5_accuracy": 0.3776223776223776,
      "val_loss": 9.41028446621365,
      "probe_path": "experiment_results/probes/k1/probe_layer_14_k1_linear.pt"
    },
    "layer15_k1": {
      "layer": 15,
      "k": 1,
      "train_accuracy": 0.08496732026143791,
      "train_loss": 9.446865510940551,
      "val_accuracy": 0.17482517482517482,
      "val_top5_accuracy": 0.32167832167832167,
      "val_loss": 7.828215863969591,
      "probe_path": "experiment_results/probes/k1/probe_layer_15_k1_linear.pt"
    }
  }
}